design.sv
module automatic_washing_machine(clk, reset, door_close, start, filled, detergent_added, cycle_timeout, drained, spin_timeout, door_lock, motor_on, fill_value_on, drain_value_on, done, soap_wash, water_wash);

	input clk, reset, door_close, start, filled, detergent_added, cycle_timeout, drained, spin_timeout;
	output reg door_lock, motor_on, fill_value_on, drain_value_on, done, soap_wash, water_wash; 
	
	//defining the states
	parameter check_door = 3'b000;
	parameter fill_water = 3'b001;
	parameter add_detergent = 3'b010;
	parameter cycle = 3'b011;
	parameter drain_water = 3'b100;
	parameter spin = 3'b101;
	
	reg[2:0] current_state, next_state;
	
	always@(current_state or start or door_close or filled or detergent_added or drained or cycle_timeout or spin_timeout)
	begin
	case(current_state)
		check_door:
			if(start==1 && door_close==1)
			begin
				next_state = fill_water;
				motor_on = 0;
				fill_value_on = 0;
				drain_value_on = 0;
				door_lock = 1;
				soap_wash = 0;
				water_wash = 0;
				done = 0;
			end
			else
			begin
				next_state = current_state;
				motor_on = 0;
				fill_value_on = 0;
				drain_value_on = 0;
				door_lock = 0;
				soap_wash = 0;
				water_wash = 0;
				done = 0;
			end
			
			fill_water:
			if (filled==1)
			begin
				if(soap_wash == 0)
				begin
					next_state = add_detergent;
					motor_on = 0;
					fill_value_on = 0;
					drain_value_on = 0;
					door_lock = 1;
					soap_wash = 1;
					water_wash = 0;
					done = 0;
				end
				else
				begin
					next_state = cycle;
					motor_on = 0;
					fill_value_on = 0;
					drain_value_on = 0;
					door_lock = 1;
					soap_wash = 1;
					water_wash = 1;
					done = 0;
				end
			end
			else
			begin
				next_state = current_state;
				motor_on = 0;
				fill_value_on = 1;
				drain_value_on = 0;
				door_lock = 1;
				done = 0;
			end
			add_detergent:
			if(detergent_added==1)
			begin
				next_state = cycle;
				motor_on = 0;
				fill_value_on = 0;
				drain_value_on = 0;
				door_lock = 1;
				soap_wash = 1;
				done = 0;
			end
			else
			begin
				next_state = current_state;
				motor_on = 0;
				fill_value_on = 0;
				drain_value_on = 0;
				door_lock = 1;
				soap_wash = 1;
				water_wash = 0;
				done = 0;
			end
			cycle:
			if(cycle_timeout == 1)
			begin
				next_state = drain_water;
				motor_on = 0;
				fill_value_on = 0;
				drain_value_on = 0;
				door_lock = 1;
				//soap_wash = 1;
				done = 0;
			end
			else
			begin
				next_state = current_state;
				motor_on = 1;
				fill_value_on = 0;
				drain_value_on = 0;
				door_lock = 1;
				//soap_wash = 1;
				done = 0;
			end
			drain_water:
			 if(drained==1)
			 begin
				if(water_wash==0)
				begin
					next_state = fill_water;
					motor_on = 0;
					fill_value_on = 0;
					drain_value_on = 0;
					door_lock = 1;
					soap_wash = 1;
					//water_wash = 1;
					done = 0;
				end
				else
				begin
				next_state = spin;
					motor_on = 0;
					fill_value_on = 0;
					drain_value_on = 0;
					door_lock = 1;
					soap_wash = 1;
					water_wash = 1;
					done = 0;
				end
			end
			else
			begin
				next_state = current_state;
				motor_on = 0;
				fill_value_on = 0;
				drain_value_on = 1;
				door_lock = 1;
				soap_wash = 1;
				//water_wash = 1;
				done = 0;
			end
			spin:
			if(spin_timeout==1)
			begin
				next_state = door_close;
				motor_on = 0;
				fill_value_on = 0;
				drain_value_on = 0;
				door_lock = 1;
				soap_wash = 1;
				water_wash = 1;
				done = 1;
			end
			else
			begin
				next_state = current_state;
				motor_on = 0;
				fill_value_on = 0;
				drain_value_on = 1;
				door_lock = 1;
				soap_wash = 1;
				water_wash = 1;
				done = 0;
			end
			default:
				next_state = check_door;
				
			endcase
	end
	
	always@(posedge clk or negedge reset)
	begin
		if(reset)
		begin
			current_state<=3'b000;
		end
		else
		begin
			current_state<=next_state;
		end
	end
	
endmodule

testbench.sv
`timescale 10ns / 1ps

module new_test();
	reg clk, reset, door_close, start, filled, detergent_added, cycle_timeout, drained, spin_timeout;
	wire door_lock, motor_on, fill_value_on, drain_value_on, done, soap_wash, water_wash; 
	
	
automatic_washing_machine machine1(clk, reset, door_close, start, filled, detergent_added, cycle_timeout, drained, spin_timeout, door_lock, motor_on, fill_value_on, drain_value_on, done, soap_wash, water_wash);


	
	
	initial
		
	begin
	clk = 0;
		reset = 1;
		start = 0;
		door_close = 0;
		filled = 0;
		drained = 0;
		detergent_added = 0;
		cycle_timeout = 0;
		spin_timeout = 0;
		
		#5 reset=0;
		#5 start=1;door_close=1;
		#10 filled=1;
		#10 detergent_added=1;
		//filled=0;
		#10 cycle_timeout=1;
		//detergent_added=0;
		#10 drained=1;
		//cycle_timeout=0;
		#10 spin_timeout=1;
		//drained=0;
		
		/*
		
		#0 reset = 0;
		#2 start = 1;
		#4 door_close = 1;
		#3 filled = 1;
		#3 detergent_added = 1;
		#2 cycle_timeout = 1;
		#2 drained = 1; 
		#3 spin_timeout = 1;
		*/
	end
	
	always
	begin
		#5 clk = ~clk;
	end
	
	initial
	begin
		$monitor("Time=%d, Clock=%b, Reset=%b, start=%b, door_close=%b, filled=%b, detergent_added=%b, cycle_timeout=%b, drained=%b, spin_timeout=%b, door_lock=%b, motor_on=%b, fill_valve_on=%b, drain_valve_on=%b, soap_wash=%b, water_wash=%b, done=%b",$time, clk, reset, start, door_close, filled, detergent_added, cycle_timeout, drained, spin_timeout, door_lock, motor_on, fill_value_on, drain_value_on, soap_wash, water_wash, done);
	end
  initial
    begin
      $dumpfile("awm.vcd");
      $dumpvars(0,new_test);
      #50 $finish;
    end
endmodule

awm.vcd
$date
	Tue Aug 22 17:44:41 2023
$end
$version
	Icarus Verilog
$end
$timescale
	1ps
$end
$scope module new_test $end
$var wire 1 ! done $end
$var wire 1 " door_lock $end
$var wire 1 # drain_value_on $end
$var wire 1 $ fill_value_on $end
$var wire 1 % motor_on $end
$var wire 1 & soap_wash $end
$var wire 1 ' water_wash $end
$var reg 1 ( clk $end
$var reg 1 ) cycle_timeout $end
$var reg 1 * detergent_added $end
$var reg 1 + door_close $end
$var reg 1 , drained $end
$var reg 1 - filled $end
$var reg 1 . reset $end
$var reg 1 / spin_timeout $end
$var reg 1 0 start $end
$scope module machine1 $end
$var wire 1 1 clk $end
$var wire 1 2 cycle_timeout $end
$var wire 1 3 detergent_added $end
$var wire 1 4 door_close $end
$var wire 1 5 drained $end
$var wire 1 6 filled $end
$var wire 1 7 reset $end
$var wire 1 8 spin_timeout $end
$var wire 1 9 start $end
$var reg 3 : current_state [2:0] $end
$var reg 1 ; done $end
$var reg 1 < door_lock $end
$var reg 1 = drain_value_on $end
$var reg 1 > fill_value_on $end
$var reg 1 ? motor_on $end
$var reg 3 @ next_state [2:0] $end
$var reg 1 A soap_wash $end
$var reg 1 B water_wash $end
$upscope $end
$upscope $end
$enddefinitions $end
#0
$dumpvars
xB
xA
b0 @
x?
x>
x=
x<
x;
bx :
09
08
17
06
05
04
03
02
01
00
0/
1.
0-
0,
0+
0*
0)
0(
x'
x&
x%
x$
x#
x"
x!
$end
#50000
0;
0!
0B
0'
0A
0&
0<
0"
0=
0#
0>
0$
0?
0%
b0 :
1(
11
0.
07
#100000
1<
1"
b1 @
0(
01
1+
14
10
19
#150000
1>
1$
b1 :
1(
11
#200000
1A
1&
0>
0$
b10 @
0(
01
1-
16
#250000
b10 :
1(
11
#300000
b11 @
0(
01
1*
13
#350000
1?
1%
b11 :
1(
11
#400000
0?
0%
b100 @
0(
01
1)
12
#450000
1=
1#
b100 :
1(
11
#500000
0=
0#
b1 @
0(
01
1,
15
